{
    "dependsOnProjects" : 
    [
        "project_System.Core_1638A83025EDAB9E9D8A1050E731FEF9D8C4C502"
    ]
    , 
    "error" : "", 
    "fileInfos" : 
    [
        {
            "content" : "", 
            "fileHash" : "4A1E4FC41EDCABBDF9673E74E61DD21B42660ACB", 
            "fileId" : "Algorithm_05E6303F5F10575C716D97CD50C237F4045C42AF", 
            "filePath" : "C:\/work\/cmajorm\/cmajor\/projects\/system-x\/system\/System.Base\/Algorithm.cm", 
            "info" : ""
        }
        , 
        {
            "content" : "", 
            "fileHash" : "BEC608E32AF0902F16FD435105761F584EDC28C9", 
            "fileId" : "AtExit_62AC7E001145C49F1A23650858B078BEB4DF19BA", 
            "filePath" : "C:\/work\/cmajorm\/cmajor\/projects\/system-x\/system\/System.Base\/AtExit.cm", 
            "info" : ""
        }
        , 
        {
            "content" : "", 
            "fileHash" : "507D40AF1B6D63F19DE9B4807E772E3E5A176D12", 
            "fileId" : "CheckedSystemCall_171CA1D78E4F5ED0DFD8BB84AC399952052E1F33", 
            "filePath" : "C:\/work\/cmajorm\/cmajor\/projects\/system-x\/system\/System.Base\/CheckedSystemCall.cm", 
            "info" : ""
        }
        , 
        {
            "content" : "", 
            "fileHash" : "A8D1016D0A3BC4B1039E161D884590D87730C9F9", 
            "fileId" : "Concept_BCA802097B7B547E376E4FD53EF025FFDADB2CBD", 
            "filePath" : "C:\/work\/cmajorm\/cmajor\/projects\/system-x\/system\/System.Base\/Concept.cm", 
            "info" : ""
        }
        , 
        {
            "content" : "", 
            "fileHash" : "0801D75DE2DF1DAFEB43435E530AD840315D2C4C", 
            "fileId" : "Conversion_39D41F477DEE10DFE6B5519892DEE65E0A82E62C", 
            "filePath" : "C:\/work\/cmajorm\/cmajor\/projects\/system-x\/system\/System.Base\/Conversion.cm", 
            "info" : ""
        }
        , 
        {
            "content" : "", 
            "fileHash" : "71CFEA739C25C756531679943588196B9D20DDDB", 
            "fileId" : "Environment_CCA2AC4632AC97BB22C8CA5FACBCF7EED9EFEFC9", 
            "filePath" : "C:\/work\/cmajorm\/cmajor\/projects\/system-x\/system\/System.Base\/Environment.cm", 
            "info" : ""
        }
        , 
        {
            "content" : "", 
            "fileHash" : "2051F527C319F65B088C462051E40F6D9EB422A8", 
            "fileId" : "Exception_6B4508E0286AB8493B8606A777AE19F82B52A33D", 
            "filePath" : "C:\/work\/cmajorm\/cmajor\/projects\/system-x\/system\/System.Base\/Exception.cm", 
            "info" : ""
        }
        , 
        {
            "content" : "", 
            "fileHash" : "C883D72D19FCF712EF6E01893B23058CA566F5DA", 
            "fileId" : "Functional_3E7571A81712D897E849DE2B733AC4B57F2FD558", 
            "filePath" : "C:\/work\/cmajorm\/cmajor\/projects\/system-x\/system\/System.Base\/Functional.cm", 
            "info" : ""
        }
        , 
        {
            "content" : "", 
            "fileHash" : "13152B5E73DA4EEF162846B707F380D419C4A16D", 
            "fileId" : "HashMap_1D7931E554DDF54DC1B298C182939ED847D73EA5", 
            "filePath" : "C:\/work\/cmajorm\/cmajor\/projects\/system-x\/system\/System.Base\/HashMap.cm", 
            "info" : ""
        }
        , 
        {
            "content" : "", 
            "fileHash" : "3E4803C7034DBE7AB5ACC05DA62C8B177720A374", 
            "fileId" : "HashSet_C2F605697B72250FBDF2602E2048B9DE656BF047", 
            "filePath" : "C:\/work\/cmajorm\/cmajor\/projects\/system-x\/system\/System.Base\/HashSet.cm", 
            "info" : ""
        }
        , 
        {
            "content" : "", 
            "fileHash" : "49C5E48D82C000E6D3C188A89C8778CB7A47CE46", 
            "fileId" : "Hashtable_4FE88ED27522BDAE20486C71016FCC3CC4C6608F", 
            "filePath" : "C:\/work\/cmajorm\/cmajor\/projects\/system-x\/system\/System.Base\/Hashtable.cm", 
            "info" : ""
        }
        , 
        {
            "content" : "", 
            "fileHash" : "F0F0D5F9E25F78AE1FDEA7D6FB346837CDCF66A0", 
            "fileId" : "List_36330085479F54F16B24CD249D8D4EBF5D0450D6", 
            "filePath" : "C:\/work\/cmajorm\/cmajor\/projects\/system-x\/system\/System.Base\/List.cm", 
            "info" : ""
        }
        , 
        {
            "content" : "", 
            "fileHash" : "8C07754F14A0917F784ED34FA35BCF9275CF346F", 
            "fileId" : "Map_84C1528F450D57284DC8FA279C4A031BED03FD2F", 
            "filePath" : "C:\/work\/cmajorm\/cmajor\/projects\/system-x\/system\/System.Base\/Map.cm", 
            "info" : ""
        }
        , 
        {
            "content" : "", 
            "fileHash" : "FF299B0ECC0BB718BA132B3D767DFE2A6CF3D1BE", 
            "fileId" : "Memory_08C7FEB12E2B2DA0CD7303EE64E9337561390435", 
            "filePath" : "C:\/work\/cmajorm\/cmajor\/projects\/system-x\/system\/System.Base\/Memory.cm", 
            "info" : ""
        }
        , 
        {
            "content" : "", 
            "fileHash" : "3B45245EE762CA6B323EC7D5A69F91C7B60102DB", 
            "fileId" : "Pair_E369D6FD990C272EFFFB289A4D1A6D44089FD9E9", 
            "filePath" : "C:\/work\/cmajorm\/cmajor\/projects\/system-x\/system\/System.Base\/Pair.cm", 
            "info" : ""
        }
        , 
        {
            "content" : "", 
            "fileHash" : "C18A9AEFCA889FD6F0D714BC29F0B5FB9363A528", 
            "fileId" : "Random_B29C88566114630C90DD06B2655AD27F949BCAB6", 
            "filePath" : "C:\/work\/cmajorm\/cmajor\/projects\/system-x\/system\/System.Base\/Random.cm", 
            "info" : ""
        }
        , 
        {
            "content" : "", 
            "fileHash" : "76122251A001A79DC3D3282E91ADC7D191717A72", 
            "fileId" : "RandomAccessIterator_278888EF96731D807ACCA71E315A9174CE5D7539", 
            "filePath" : "C:\/work\/cmajorm\/cmajor\/projects\/system-x\/system\/System.Base\/RandomAccessIterator.cm", 
            "info" : ""
        }
        , 
        {
            "content" : "", 
            "fileHash" : "F010A8765C165F3D6CA6DFEEFA93AC89DE1BFAF9", 
            "fileId" : "RedBlackTree_AC46C5F18D5C3422AC5F885BB2576373E065B318", 
            "filePath" : "C:\/work\/cmajorm\/cmajor\/projects\/system-x\/system\/System.Base\/RedBlackTree.cm", 
            "info" : ""
        }
        , 
        {
            "content" : "", 
            "fileHash" : "F6C582536CCE702903690993DEA356A20716EDA5", 
            "fileId" : "Rvalue_932D5719953D808AA9237CA53A8B3350DACC17DF", 
            "filePath" : "C:\/work\/cmajorm\/cmajor\/projects\/system-x\/system\/System.Base\/Rvalue.cm", 
            "info" : ""
        }
        , 
        {
            "content" : "", 
            "fileHash" : "76680ADE62BD4D8F4D36B5FB1A84EB5C3580DC81", 
            "fileId" : "Set_3BED6B6DDD11033D2C4485602D7E0BF3721ED05B", 
            "filePath" : "C:\/work\/cmajorm\/cmajor\/projects\/system-x\/system\/System.Base\/Set.cm", 
            "info" : ""
        }
        , 
        {
            "content" : "", 
            "fileHash" : "2F75D7BFF87BDE9DD83E11B599B63288233F1573", 
            "fileId" : "String_A754D158598C294062AC74D034FD8F17ADA3EEF2", 
            "filePath" : "C:\/work\/cmajorm\/cmajor\/projects\/system-x\/system\/System.Base\/String.cm", 
            "info" : ""
        }
        , 
        {
            "content" : "", 
            "fileHash" : "3FE00DAEEDDA333C551BB0D07BDC55EACA8D9F52", 
            "fileId" : "SystemCall_556B61B7CE8AB2BF95F1BE319E3718E2AF648CA8", 
            "filePath" : "C:\/work\/cmajorm\/cmajor\/projects\/system-x\/system\/System.Base\/SystemCall.cm", 
            "info" : ""
        }
        , 
        {
            "content" : "", 
            "fileHash" : "ECF45CCCD962D58E1AEF800661CB97A463375D44", 
            "fileId" : "SystemError_D4FFD79F96B136B08B3A5453B159E8F7DCDE2CB0", 
            "filePath" : "C:\/work\/cmajorm\/cmajor\/projects\/system-x\/system\/System.Base\/SystemError.cm", 
            "info" : ""
        }
        , 
        {
            "content" : "", 
            "fileHash" : "6625186DB006082F0D1440EAD6D3A9D54B0F6007", 
            "fileId" : "Time_3D6299402C7AF96FA241B67254501C0A687E68F6", 
            "filePath" : "C:\/work\/cmajorm\/cmajor\/projects\/system-x\/system\/System.Base\/Time.cm", 
            "info" : ""
        }
        , 
        {
            "content" : "", 
            "fileHash" : "0CA649EE15B2E6C4B69EF39B45A7E646FFD6E8B8", 
            "fileId" : "UniquePtr_E2E5CD9585D07A289EA72FDFA2A818BE12A43436", 
            "filePath" : "C:\/work\/cmajorm\/cmajor\/projects\/system-x\/system\/System.Base\/UniquePtr.cm", 
            "info" : ""
        }
        , 
        {
            "content" : "", 
            "fileHash" : "C6D66B8FEC9E491C74C92AC57B1B06E999A6868F", 
            "fileId" : "Utility_7A1CB71891AC5463B0580443C5BB364A1DFE65ED", 
            "filePath" : "C:\/work\/cmajorm\/cmajor\/projects\/system-x\/system\/System.Base\/Utility.cm", 
            "info" : ""
        }
        , 
        {
            "content" : "", 
            "fileHash" : "36AB2895D10A05B6CE7BD98B540EFA9D5C4131FF", 
            "fileId" : "Uuid_8E93EBE0CD87846987075B54D574C961986A3D36", 
            "filePath" : "C:\/work\/cmajorm\/cmajor\/projects\/system-x\/system\/System.Base\/Uuid.cm", 
            "info" : ""
        }
    ]
    , 
    "info" : "", 
    "projectFilePath" : "C:\/work\/cmajorm\/cmajor\/projects\/system-x\/system\/System.Base\/System.Base.cmp", 
    "projectHash" : "7F88EC7152E9FA8787D243BA553707F5D1A83C10", 
    "projectId" : "project_System.Base_4080984F3C6E57264543260DB64C38B6220EE6E0", 
    "projectName" : "System.Base", 
    "target" : "library"
}
