{
    "dependsOnProjects" : 
    [
        "project_paths_B11AEA98A7D0FB5060C4BF5E99774CB64C5CE007"
    ]
    , 
    "error" : "", 
    "fileInfos" : 
    [
        {
            "content" : "", 
            "fileHash" : "2F36FA7D581DBDD42DC884A36F8A59E32D481B43", 
            "fileId" : "help_8E903CF878CEA98605B7044939FE7E61F887DB5D", 
            "filePath" : "C:\/work\/cmajorm\/cmajor\/system-x\/projects\/coreutil\/cp\/help.cm", 
            "info" : ""
        }
        , 
        {
            "content" : "", 
            "fileHash" : "50259C4F3E9A38E6C9BF33ABE36BD46A8D05647C", 
            "fileId" : "main_51CED3481891BDCF26CC728758187FA399F0D437", 
            "filePath" : "C:\/work\/cmajorm\/cmajor\/system-x\/projects\/coreutil\/cp\/main.cm", 
            "info" : ""
        }
        , 
        {
            "content" : "", 
            "fileHash" : "7145679E5F8A156A2E53F9F9D39B58C66A99C89B", 
            "fileId" : "cp_209752DA6C67A1F27B24421A1B58B17655A07AFD", 
            "filePath" : "C:\/work\/cmajorm\/cmajor\/system-x\/projects\/coreutil\/cp\/cp.cm", 
            "info" : ""
        }
    ]
    , 
    "info" : "", 
    "projectFilePath" : "C:\/work\/cmajorm\/cmajor\/system-x\/projects\/coreutil\/cp\/cp.cmp", 
    "projectHash" : "A2161C8245C7F244062A647AA5182F04E5F65507", 
    "projectId" : "project_cp_7BB27C530ACA8C07F6A1058C770443CAB3667EA1", 
    "projectName" : "cp", 
    "target" : "program"
}
