{
    "dependsOnProjects" : 
    [
        "project_Cm.Ast_BFF232E4680A917E861A5833139E3F88D9862A65", 
        "project_Cm.Nothrow.Lexer_7AE12F197C21243B0CACE9382A86B7A66954157F", 
        "project_Cm.Nothrow.Parser_8E7EA6BD39D0E27C1715F9817E4A5346C2A267CC"
    ]
    , 
    "error" : "", 
    "fileInfos" : 
    [
        {
            "content" : "", 
            "fileHash" : "778DDF465BFB05BF472CA6AF1046E60E15A65EB2", 
            "fileId" : "Module_3A7DD76C44AF785D78305F31CF053B7D84DACFC1", 
            "filePath" : "C:\/work\/cmajorm\/cmajor\/projects\/cm\/symbols\/Module.cm", 
            "info" : ""
        }
        , 
        {
            "content" : "", 
            "fileHash" : "86E03FB4FBA1AC8BB2D984B22B8F33651815DBF6", 
            "fileId" : "ModuleCache_EF3EAE1E678CBA3290CE800D6540E3B7BBC00A3D", 
            "filePath" : "C:\/work\/cmajorm\/cmajor\/projects\/cm\/symbols\/ModuleCache.cm", 
            "info" : ""
        }
        , 
        {
            "content" : "", 
            "fileHash" : "E304511778278FDDB939A441C498C4BAA9FD80E2", 
            "fileId" : "Sources_17F716AC26D8F4DF349A6073AF97171FA08CF877", 
            "filePath" : "C:\/work\/cmajorm\/cmajor\/projects\/cm\/symbols\/Sources.cm", 
            "info" : ""
        }
        , 
        {
            "content" : "", 
            "fileHash" : "5A2058C70814E054FB05F4706A0B9E6119A40864", 
            "fileId" : "Symbol_36E629B2583E4015BAEEC871E0582876BC1746FB", 
            "filePath" : "C:\/work\/cmajorm\/cmajor\/projects\/cm\/symbols\/Symbol.cm", 
            "info" : ""
        }
        , 
        {
            "content" : "", 
            "fileHash" : "15ACE17931FD25D063171EBEB22010EAE27CA8B6", 
            "fileId" : "SymbolReader_4762975DA59DA4F097DF9E2AE2DD58D1452B7ACA", 
            "filePath" : "C:\/work\/cmajorm\/cmajor\/projects\/cm\/symbols\/SymbolReader.cm", 
            "info" : ""
        }
        , 
        {
            "content" : "", 
            "fileHash" : "2C4300031B963C3152180D76AA59CF865A897A70", 
            "fileId" : "SymbolWriter_07E74796B7C3C084824BDA3B93D725154932D62A", 
            "filePath" : "C:\/work\/cmajorm\/cmajor\/projects\/cm\/symbols\/SymbolWriter.cm", 
            "info" : ""
        }
    ]
    , 
    "info" : "", 
    "projectFilePath" : "C:\/work\/cmajorm\/cmajor\/projects\/cm\/symbols\/Cm.Symbols.cmp", 
    "projectHash" : "101C530CBD889B51BCED02C4CB167DD4AE3F86D0", 
    "projectId" : "project_Cm.Symbols_800DC3ED99901AA8C7F615A139BB50095AF19E8D", 
    "projectName" : "Cm.Symbols", 
    "target" : "library"
}
