<profile elapsed="1428517" project="HexDump">
  <function count="3" elapsedExclusive="277" elapsedExclusivePercent="0.1" elapsedInclusive="9427" elapsedInclusivePercent="0.6" id="1150750" name="Counter&lt;System.IO.ByteStream>.@constructor(Counter&lt;System.IO.ByteStream>, ByteStream*)"/>
  <function count="3" elapsedExclusive="0" elapsedExclusivePercent="0" elapsedInclusive="1663" elapsedInclusivePercent="0.1" id="1150755" name="Counter&lt;System.IO.ByteStream>.Dispose(Counter&lt;System.IO.ByteStream>)"/>
  <function count="1" elapsedExclusive="1386" elapsedExclusivePercent="0.5" elapsedInclusive="1128783" elapsedInclusivePercent="79.0" id="1291742" name="HexDump(const String&lt;char>&amp;)"/>
  <function count="2" elapsedExclusive="554" elapsedExclusivePercent="0.2" elapsedInclusive="554" elapsedInclusivePercent="0.0" id="1169028" name="List&lt;String&lt;char>>.@constructor(List&lt;String&lt;char>>)"/>
  <function count="2" elapsedExclusive="277" elapsedExclusivePercent="0.1" elapsedInclusive="277" elapsedInclusivePercent="0.0" id="1150849" name="List&lt;String&lt;char>>.@constructor(List&lt;String&lt;char>>, List&lt;String&lt;char>>&amp;&amp;)"/>
  <function count="4" elapsedExclusive="0" elapsedExclusivePercent="0" elapsedInclusive="11370" elapsedInclusivePercent="0.7" id="1169034" name="List&lt;String&lt;char>>.@destructor(List&lt;String&lt;char>>)"/>
  <function count="8" elapsedExclusive="277" elapsedExclusivePercent="0.1" elapsedInclusive="4436" elapsedInclusivePercent="0.3" id="1150861" name="List&lt;String&lt;char>>.Add(List&lt;String&lt;char>>, String&lt;char>&amp;&amp;)"/>
  <function count="1" elapsedExclusive="0" elapsedExclusivePercent="0" elapsedInclusive="3050" elapsedInclusivePercent="0.2" id="1291928" name="List&lt;String&lt;char>>.Add(List&lt;String&lt;char>>, const String&lt;char>&amp;)"/>
  <function count="1" elapsedExclusive="0" elapsedExclusivePercent="0" elapsedInclusive="277" elapsedInclusivePercent="0.0" id="1291939" name="List&lt;String&lt;char>>.Begin(List&lt;String&lt;char>>)"/>
  <function count="1" elapsedExclusive="0" elapsedExclusivePercent="0" elapsedInclusive="0" elapsedInclusivePercent="0" id="1169037" name="List&lt;String&lt;char>>.Count(const List&lt;String&lt;char>>)"/>
  <function count="4" elapsedExclusive="0" elapsedExclusivePercent="0" elapsedInclusive="10815" elapsedInclusivePercent="0.7" id="1169063" name="List&lt;String&lt;char>>.Destroy(List&lt;String&lt;char>>)"/>
  <function count="1" elapsedExclusive="0" elapsedExclusivePercent="0" elapsedInclusive="277" elapsedInclusivePercent="0.0" id="1291942" name="List&lt;String&lt;char>>.End(List&lt;String&lt;char>>)"/>
  <function count="2" elapsedExclusive="0" elapsedExclusivePercent="0" elapsedInclusive="832" elapsedInclusivePercent="0.0" id="1169062" name="List&lt;String&lt;char>>.Grow(List&lt;String&lt;char>>, long)"/>
  <function count="1" elapsedExclusive="0" elapsedExclusivePercent="0" elapsedInclusive="0" elapsedInclusivePercent="0" id="1291926" name="List&lt;String&lt;char>>.IsEmpty(const List&lt;String&lt;char>>)"/>
  <function count="9" elapsedExclusive="277" elapsedExclusivePercent="0.1" elapsedInclusive="2773" elapsedInclusivePercent="0.1" id="1169035" name="List&lt;String&lt;char>>.Reserve(List&lt;String&lt;char>>, long)"/>
  <function count="16" elapsedExclusive="832" elapsedExclusivePercent="0.3" elapsedInclusive="832" elapsedInclusivePercent="0.0" id="1169051" name="List&lt;String&lt;char>>.operator[](List&lt;String&lt;char>>, long)"/>
  <function count="2" elapsedExclusive="0" elapsedExclusivePercent="0" elapsedInclusive="0" elapsedInclusivePercent="0" id="1291960" name="RandomAccessIter&lt;String&lt;char>, String&lt;char>&amp;, String&lt;char>*>.@constructor(RandomAccessIter&lt;String&lt;char>, String&lt;char>&amp;, String&lt;char>*>, String&lt;char>*)"/>
  <function count="2" elapsedExclusive="277" elapsedExclusivePercent="0.1" elapsedInclusive="277" elapsedInclusivePercent="0.0" id="1291966" name="RandomAccessIter&lt;String&lt;char>, String&lt;char>&amp;, String&lt;char>*>.Ptr(const RandomAccessIter&lt;String&lt;char>, String&lt;char>&amp;, String&lt;char>*>)"/>
  <function count="1" elapsedExclusive="0" elapsedExclusivePercent="0" elapsedInclusive="0" elapsedInclusivePercent="0" id="1291963" name="RandomAccessIter&lt;String&lt;char>, String&lt;char>&amp;, String&lt;char>*>.operator*(RandomAccessIter&lt;String&lt;char>, String&lt;char>&amp;, String&lt;char>*>)"/>
  <function count="6" elapsedExclusive="832" elapsedExclusivePercent="0.3" elapsedInclusive="832" elapsedInclusivePercent="0.0" id="1150832" name="RandomAccessIter&lt;char, const char&amp;, const char*>.@constructor(RandomAccessIter&lt;char, const char&amp;, const char*>, const char*)"/>
  <function count="132" elapsedExclusive="11922" elapsedExclusivePercent="4.8" elapsedInclusive="11922" elapsedInclusivePercent="0.8" id="1150838" name="RandomAccessIter&lt;char, const char&amp;, const char*>.Ptr(const RandomAccessIter&lt;char, const char&amp;, const char*>)"/>
  <function count="63" elapsedExclusive="11645" elapsedExclusivePercent="4.7" elapsedInclusive="11645" elapsedInclusivePercent="0.8" id="1150835" name="RandomAccessIter&lt;char, const char&amp;, const char*>.operator*(RandomAccessIter&lt;char, const char&amp;, const char*>)"/>
  <function count="63" elapsedExclusive="5823" elapsedExclusivePercent="2.3" elapsedInclusive="5823" elapsedInclusivePercent="0.4" id="1150833" name="RandomAccessIter&lt;char, const char&amp;, const char*>.operator++(RandomAccessIter&lt;char, const char&amp;, const char*>)"/>
  <function count="3" elapsedExclusive="0" elapsedExclusivePercent="0" elapsedInclusive="10537" elapsedInclusivePercent="0.7" id="1150738" name="SharedCount&lt;System.IO.ByteStream>.@constructor(SharedCount&lt;System.IO.ByteStream>, ByteStream*)"/>
  <function count="3" elapsedExclusive="0" elapsedExclusivePercent="0" elapsedInclusive="0" elapsedInclusivePercent="0" id="1150741" name="SharedCount&lt;System.IO.ByteStream>.@constructor(SharedCount&lt;System.IO.ByteStream>, SharedCount&lt;System.IO.ByteStream>&amp;&amp;)"/>
  <function count="3" elapsedExclusive="0" elapsedExclusivePercent="0" elapsedInclusive="832" elapsedInclusivePercent="0.0" id="1150740" name="SharedCount&lt;System.IO.ByteStream>.@constructor(SharedCount&lt;System.IO.ByteStream>, const SharedCount&lt;System.IO.ByteStream>&amp;)"/>
  <function count="9" elapsedExclusive="277" elapsedExclusivePercent="0.1" elapsedInclusive="4991" elapsedInclusivePercent="0.3" id="1150745" name="SharedCount&lt;System.IO.ByteStream>.@destructor(SharedCount&lt;System.IO.ByteStream>)"/>
  <function count="3" elapsedExclusive="0" elapsedExclusivePercent="0" elapsedInclusive="11368" elapsedInclusivePercent="0.7" id="1150719" name="SharedPtr&lt;System.IO.ByteStream>.@constructor(SharedPtr&lt;System.IO.ByteStream>, ByteStream*)"/>
  <function count="3" elapsedExclusive="0" elapsedExclusivePercent="0" elapsedInclusive="832" elapsedInclusivePercent="0.0" id="1150722" name="SharedPtr&lt;System.IO.ByteStream>.@constructor(SharedPtr&lt;System.IO.ByteStream>, SharedPtr&lt;System.IO.ByteStream>&amp;&amp;)"/>
  <function count="3" elapsedExclusive="277" elapsedExclusivePercent="0.1" elapsedInclusive="1386" elapsedInclusivePercent="0.0" id="1150721" name="SharedPtr&lt;System.IO.ByteStream>.@constructor(SharedPtr&lt;System.IO.ByteStream>, const SharedPtr&lt;System.IO.ByteStream>&amp;)"/>
  <function count="4" elapsedExclusive="832" elapsedExclusivePercent="0.3" elapsedInclusive="832" elapsedInclusivePercent="0.0" id="1150728" name="SharedPtr&lt;System.IO.ByteStream>.operator->(const SharedPtr&lt;System.IO.ByteStream>)"/>
  <function count="4" elapsedExclusive="554" elapsedExclusivePercent="0.2" elapsedInclusive="554" elapsedInclusivePercent="0.0" id="1168965" name="String&lt;char>.@constructor(String&lt;char>)"/>
  <function count="33" elapsedExclusive="2221" elapsedExclusivePercent="0.9" elapsedInclusive="2221" elapsedInclusivePercent="0.1" id="1168970" name="String&lt;char>.@constructor(String&lt;char>, String&lt;char>&amp;&amp;)"/>
  <function count="14" elapsedExclusive="0" elapsedExclusivePercent="0" elapsedInclusive="14972" elapsedInclusivePercent="1.0" id="1168969" name="String&lt;char>.@constructor(String&lt;char>, const String&lt;char>&amp;)"/>
  <function count="28" elapsedExclusive="277" elapsedExclusivePercent="0.1" elapsedInclusive="130322" elapsedInclusivePercent="9.1" id="1168966" name="String&lt;char>.@constructor(String&lt;char>, const char*)"/>
  <function count="7" elapsedExclusive="278" elapsedExclusivePercent="0.1" elapsedInclusive="7208" elapsedInclusivePercent="0.5" id="1150786" name="String&lt;char>.@constructor(String&lt;char>, const char*, long)"/>
  <function count="79" elapsedExclusive="277" elapsedExclusivePercent="0.1" elapsedInclusive="34937" elapsedInclusivePercent="2.4" id="1168975" name="String&lt;char>.@destructor(String&lt;char>)"/>
  <function count="71" elapsedExclusive="0" elapsedExclusivePercent="0" elapsedInclusive="35216" elapsedInclusivePercent="2.4" id="1150803" name="String&lt;char>.Append(String&lt;char>, char)"/>
  <function count="14" elapsedExclusive="0" elapsedExclusivePercent="0" elapsedInclusive="41595" elapsedInclusivePercent="2.9" id="1168988" name="String&lt;char>.Append(String&lt;char>, const String&lt;char>&amp;)"/>
  <function count="4" elapsedExclusive="0" elapsedExclusivePercent="0" elapsedInclusive="13864" elapsedInclusivePercent="0.9" id="1168986" name="String&lt;char>.Append(String&lt;char>, const char*)"/>
  <function count="18" elapsedExclusive="0" elapsedExclusivePercent="0" elapsedInclusive="42427" elapsedInclusivePercent="2.9" id="1169009" name="String&lt;char>.AppendFrom(String&lt;char>, const char*, long)"/>
  <function count="3" elapsedExclusive="0" elapsedExclusivePercent="0" elapsedInclusive="831" elapsedInclusivePercent="0.0" id="1150813" name="String&lt;char>.CBegin(const String&lt;char>)"/>
  <function count="3" elapsedExclusive="0" elapsedExclusivePercent="0" elapsedInclusive="1111" elapsedInclusivePercent="0.0" id="1150816" name="String&lt;char>.CEnd(const String&lt;char>)"/>
  <function count="5" elapsedExclusive="555" elapsedExclusivePercent="0.2" elapsedInclusive="555" elapsedInclusivePercent="0.0" id="1150799" name="String&lt;char>.Chars(const String&lt;char>)"/>
  <function count="1" elapsedExclusive="0" elapsedExclusivePercent="0" elapsedInclusive="278" elapsedInclusivePercent="0.0" id="1150798" name="String&lt;char>.Clear(String&lt;char>)"/>
  <function count="80" elapsedExclusive="0" elapsedExclusivePercent="0" elapsedInclusive="22185" elapsedInclusivePercent="1.5" id="1169011" name="String&lt;char>.Deallocate(String&lt;char>)"/>
  <function count="59" elapsedExclusive="0" elapsedExclusivePercent="0" elapsedInclusive="86786" elapsedInclusivePercent="6.0" id="1169010" name="String&lt;char>.Grow(String&lt;char>, long)"/>
  <function count="12" elapsedExclusive="554" elapsedExclusivePercent="0.2" elapsedInclusive="554" elapsedInclusivePercent="0.0" id="1168978" name="String&lt;char>.IsEmpty(const String&lt;char>)"/>
  <function count="46" elapsedExclusive="4713" elapsedExclusivePercent="1.9" elapsedInclusive="4713" elapsedInclusivePercent="0.3" id="1150795" name="String&lt;char>.Length(const String&lt;char>)"/>
  <function count="138" elapsedExclusive="277" elapsedExclusivePercent="0.1" elapsedInclusive="101757" elapsedInclusivePercent="7.1" id="1168983" name="String&lt;char>.Reserve(String&lt;char>, long)"/>
  <function count="1" elapsedExclusive="0" elapsedExclusivePercent="0" elapsedInclusive="47414" elapsedInclusivePercent="3.3" id="1150819" name="String&lt;char>.Split(String&lt;char>, char)"/>
  <function count="1" elapsedExclusive="0" elapsedExclusivePercent="0" elapsedInclusive="8041" elapsedInclusivePercent="0.5" id="1291885" name="String&lt;char>.StartsWith(const String&lt;char>, const String&lt;char>&amp;)"/>
  <function count="1" elapsedExclusive="0" elapsedExclusivePercent="0" elapsedInclusive="25232" elapsedInclusivePercent="1.7" id="1150809" name="String&lt;char>.Substring(const String&lt;char>, long)"/>
  <function count="7" elapsedExclusive="0" elapsedExclusivePercent="0" elapsedInclusive="10814" elapsedInclusivePercent="0.7" id="1150810" name="String&lt;char>.Substring(const String&lt;char>, long, long)"/>
  <function count="6" elapsedExclusive="277" elapsedExclusivePercent="0.1" elapsedInclusive="277" elapsedInclusivePercent="0.0" id="1150801" name="String&lt;char>.operator[](String&lt;char>, long)"/>
  <function count="3" elapsedExclusive="555" elapsedExclusivePercent="0.2" elapsedInclusive="555" elapsedInclusivePercent="0.0" id="1150800" name="String&lt;char>.operator[](const String&lt;char>, long)"/>
  <function count="1" elapsedExclusive="0" elapsedExclusivePercent="0" elapsedInclusive="4159" elapsedInclusivePercent="0.2" id="1149507" name="System.Ascii.CharClassTable.@constructor(System.Ascii.CharClassTable)"/>
  <function count="2" elapsedExclusive="0" elapsedExclusivePercent="0" elapsedInclusive="18300" elapsedInclusivePercent="1.2" id="1149504" name="System.Ascii.CharClassTable.@static_constructor()"/>
  <function count="1" elapsedExclusive="0" elapsedExclusivePercent="0" elapsedInclusive="0" elapsedInclusivePercent="0" id="1149506" name="System.Ascii.CharClassTable.GetCharacterClass(System.Ascii.CharClassTable, char)"/>
  <function count="1" elapsedExclusive="0" elapsedExclusivePercent="0" elapsedInclusive="25786" elapsedInclusivePercent="1.8" id="1149505" name="System.Ascii.CharClassTable.Instance()"/>
  <function count="16" elapsedExclusive="2218" elapsedExclusivePercent="0.9" elapsedInclusive="2218" elapsedInclusivePercent="0.1" id="1149508" name="System.Ascii.CharClassTable.SetCharacterClass(System.Ascii.CharClassTable, byte, byte, System.Ascii.CharClass)"/>
  <function count="2" elapsedExclusive="277" elapsedExclusivePercent="0.1" elapsedInclusive="9705" elapsedInclusivePercent="0.6" id="1178984" name="System.Collections.Destroy(String&lt;char>*, long)"/>
  <function count="2" elapsedExclusive="0" elapsedExclusivePercent="0" elapsedInclusive="67932" elapsedInclusivePercent="4.7" id="1149655" name="System.Console.@static_constructor()"/>
  <function count="1" elapsedExclusive="0" elapsedExclusivePercent="0" elapsedInclusive="554" elapsedInclusivePercent="0.0" id="1149700" name="System.Console.Error()"/>
  <function count="1" elapsedExclusive="0" elapsedExclusivePercent="0" elapsedInclusive="95105" elapsedInclusivePercent="6.6" id="1149679" name="System.Console.WriteLine(const String&lt;char>&amp;)"/>
  <function count="3" elapsedExclusive="0" elapsedExclusivePercent="0" elapsedInclusive="0" elapsedInclusivePercent="0" id="1150028" name="System.CounterBase.@constructor(System.CounterBase)"/>
  <function count="3" elapsedExclusive="0" elapsedExclusivePercent="0" elapsedInclusive="0" elapsedInclusivePercent="0" id="1150036" name="System.CounterBase.AddReference(System.CounterBase)"/>
  <function count="3" elapsedExclusive="278" elapsedExclusivePercent="0.1" elapsedInclusive="278" elapsedInclusivePercent="0.0" id="1150035" name="System.CounterBase.Destruct(System.CounterBase)"/>
  <function count="6" elapsedExclusive="0" elapsedExclusivePercent="0" elapsedInclusive="3604" elapsedInclusivePercent="0.2" id="1150037" name="System.CounterBase.Release(System.CounterBase)"/>
  <function count="3" elapsedExclusive="0" elapsedExclusivePercent="0" elapsedInclusive="833" elapsedInclusivePercent="0.0" id="1150039" name="System.CounterBase.WeakRelease(System.CounterBase)"/>
  <function count="3" elapsedExclusive="277" elapsedExclusivePercent="0.1" elapsedInclusive="277" elapsedInclusivePercent="0.0" id="1158901" name="System.EnableSharedFromThis(void*, void*, const SharedCount&lt;System.IO.ByteStream>&amp;)"/>
  <function count="1" elapsedExclusive="0" elapsedExclusivePercent="0" elapsedInclusive="0" elapsedInclusivePercent="0" id="1150135" name="System.Endl.@constructor(System.Endl)"/>
  <function count="1" elapsedExclusive="1109" elapsedExclusivePercent="0.4" elapsedInclusive="168859" elapsedInclusivePercent="11.8" id="1149769" name="System.Exception.@constructor(System.Exception, const String&lt;char>&amp;)"/>
  <function count="1" elapsedExclusive="0" elapsedExclusivePercent="0" elapsedInclusive="64327" elapsedInclusivePercent="4.5" id="1149773" name="System.Exception.ToString(const Exception)"/>
  <function count="1" elapsedExclusive="0" elapsedExclusivePercent="0" elapsedInclusive="656863" elapsedInclusivePercent="45.9" id="1149784" name="System.IO.File.Size(const String&lt;char>&amp;)"/>
  <function count="3" elapsedExclusive="555" elapsedExclusivePercent="0.2" elapsedInclusive="555" elapsedInclusivePercent="0.0" id="1149793" name="System.IO.FileByteStream.@constructor(System.IO.FileByteStream, int)"/>
  <function count="3" elapsedExclusive="277" elapsedExclusivePercent="0.1" elapsedInclusive="1109" elapsedInclusivePercent="0.0" id="1149799" name="System.IO.FileByteStream.@destructor(System.IO.FileByteStream)"/>
  <function count="3" elapsedExclusive="0" elapsedExclusivePercent="0" elapsedInclusive="0" elapsedInclusivePercent="0" id="1149802" name="System.IO.FileByteStream.Close(System.IO.FileByteStream)"/>
  <function count="4" elapsedExclusive="22182" elapsedExclusivePercent="9.0" elapsedInclusive="22182" elapsedInclusivePercent="1.5" id="1149806" name="System.IO.FileByteStream.Write(System.IO.FileByteStream, byte*, long)"/>
  <function count="1" elapsedExclusive="832" elapsedExclusivePercent="0.3" elapsedInclusive="169691" elapsedInclusivePercent="11.8" id="1149809" name="System.IO.FileSystemException.@constructor(System.IO.FileSystemException, const String&lt;char>&amp;)"/>
  <function count="1" elapsedExclusive="0" elapsedExclusivePercent="0" elapsedInclusive="103423" elapsedInclusivePercent="7.2" id="1149983" name="System.IO.GetCurrentWorkingDirectory()"/>
  <function count="1" elapsedExclusive="0" elapsedExclusivePercent="0" elapsedInclusive="341047" elapsedInclusivePercent="23.8" id="1149984" name="System.IO.GetFullPath(const String&lt;char>&amp;)"/>
  <function count="1" elapsedExclusive="0" elapsedExclusivePercent="0" elapsedInclusive="54900" elapsedInclusivePercent="3.8" id="1149993" name="System.IO.Path.IsAbsolute(const String&lt;char>&amp;)"/>
  <function count="1" elapsedExclusive="0" elapsedExclusivePercent="0" elapsedInclusive="54900" elapsedInclusivePercent="3.8" id="1149994" name="System.IO.Path.IsRelative(const String&lt;char>&amp;)"/>
  <function count="3" elapsedExclusive="0" elapsedExclusivePercent="0" elapsedInclusive="163870" elapsedInclusivePercent="11.4" id="1149985" name="System.IO.Path.MakeCanonical(const String&lt;char>&amp;)"/>
  <function count="1" elapsedExclusive="277" elapsedExclusivePercent="0.1" elapsedInclusive="831" elapsedInclusivePercent="0.0" id="1150137" name="System.IO.StreamReader.@constructor(System.IO.StreamReader, const SharedPtr&lt;System.IO.ByteStream>&amp;)"/>
  <function count="2" elapsedExclusive="0" elapsedExclusivePercent="0" elapsedInclusive="1386" elapsedInclusivePercent="0.0" id="1150146" name="System.IO.StreamWriter.@constructor(System.IO.StreamWriter, const SharedPtr&lt;System.IO.ByteStream>&amp;)"/>
  <function count="4" elapsedExclusive="0" elapsedExclusivePercent="0" elapsedInclusive="26064" elapsedInclusivePercent="1.8" id="1150147" name="System.IO.StreamWriter.Write(System.IO.StreamWriter, const String&lt;char>&amp;)"/>
  <function count="2" elapsedExclusive="0" elapsedExclusivePercent="0" elapsedInclusive="9151" elapsedInclusivePercent="0.6" id="1150166" name="System.IO.StreamWriter.WriteLine(System.IO.StreamWriter)"/>
  <function count="1" elapsedExclusive="0" elapsedExclusivePercent="0" elapsedInclusive="7486" elapsedInclusivePercent="0.5" id="1150167" name="System.IO.StreamWriter.WriteLine(System.IO.StreamWriter, const String&lt;char>&amp;)"/>
  <function count="1" elapsedExclusive="0" elapsedExclusivePercent="0" elapsedInclusive="6378" elapsedInclusivePercent="0.4" id="1150206" name="System.IO.operator&lt;&lt;(StreamWriter&amp;, const Endl&amp;)"/>
  <function count="1" elapsedExclusive="0" elapsedExclusivePercent="0" elapsedInclusive="17468" elapsedInclusivePercent="1.2" id="1150187" name="System.IO.operator&lt;&lt;(StreamWriter&amp;, const String&lt;char>&amp;)"/>
  <function count="1" elapsedExclusive="277" elapsedExclusivePercent="0.1" elapsedInclusive="34382" elapsedInclusivePercent="2.4" id="1149511" name="System.IsAlpha(char)"/>
  <function count="61" elapsedExclusive="49077" elapsedExclusivePercent="20.0" elapsedInclusive="49077" elapsedInclusivePercent="3.4" id="1150657" name="System.MemAlloc(long)"/>
  <function count="58" elapsedExclusive="26338" elapsedExclusivePercent="10.7" elapsedInclusive="26338" elapsedInclusivePercent="1.8" id="1150659" name="System.MemFree(void*)"/>
  <function count="61" elapsedExclusive="3603" elapsedExclusivePercent="1.4" elapsedInclusive="3603" elapsedInclusivePercent="0.2" id="1150656" name="System.MemGrow(long)"/>
  <function count="2" elapsedExclusive="555" elapsedExclusivePercent="0.2" elapsedInclusive="555" elapsedInclusivePercent="0.0" id="990204" name="System.Runtime.StaticInitCriticalSection.@constructor(System.Runtime.StaticInitCriticalSection, uint)"/>
  <function count="2" elapsedExclusive="554" elapsedExclusivePercent="0.2" elapsedInclusive="554" elapsedInclusivePercent="0.0" id="990205" name="System.Runtime.StaticInitCriticalSection.@destructor(System.Runtime.StaticInitCriticalSection)"/>
  <function count="1" elapsedExclusive="0" elapsedExclusivePercent="0" elapsedInclusive="0" elapsedInclusivePercent="0" id="1158968" name="System.Rvalue(List&lt;String&lt;char>>&amp;&amp;)"/>
  <function count="3" elapsedExclusive="0" elapsedExclusivePercent="0" elapsedInclusive="0" elapsedInclusivePercent="0" id="1158903" name="System.Rvalue(SharedCount&lt;System.IO.ByteStream>&amp;&amp;)"/>
  <function count="3" elapsedExclusive="0" elapsedExclusivePercent="0" elapsedInclusive="0" elapsedInclusivePercent="0" id="1158902" name="System.Rvalue(SharedPtr&lt;System.IO.ByteStream>&amp;&amp;)"/>
  <function count="14" elapsedExclusive="1940" elapsedExclusivePercent="0.7" elapsedInclusive="1940" elapsedInclusivePercent="0.1" id="1178982" name="System.Rvalue(String&lt;char>&amp;&amp;)"/>
  <function count="4" elapsedExclusive="554" elapsedExclusivePercent="0.2" elapsedInclusive="554" elapsedInclusivePercent="0.0" id="1308657" name="System.Rvalue(String&lt;char>*&amp;&amp;)"/>
  <function count="2" elapsedExclusive="0" elapsedExclusivePercent="0" elapsedInclusive="0" elapsedInclusivePercent="0" id="1178945" name="System.Rvalue(bool&amp;&amp;)"/>
  <function count="12" elapsedExclusive="554" elapsedExclusivePercent="0.2" elapsedInclusive="554" elapsedInclusivePercent="0.0" id="1158867" name="System.Rvalue(const char*&amp;&amp;)"/>
  <function count="1" elapsedExclusive="0" elapsedExclusivePercent="0" elapsedInclusive="0" elapsedInclusivePercent="0" id="1178946" name="System.Rvalue(int&amp;&amp;)"/>
  <function count="47" elapsedExclusive="8041" elapsedExclusivePercent="3.2" elapsedInclusive="8041" elapsedInclusivePercent="0.5" id="1150650" name="System.StrCopy(char*, const char*)"/>
  <function count="25" elapsedExclusive="6100" elapsedExclusivePercent="2.4" elapsedInclusive="6100" elapsedInclusivePercent="0.4" id="1150653" name="System.StrCopy(char*, const char*, long)"/>
  <function count="32" elapsedExclusive="58229" elapsedExclusivePercent="23.8" elapsedInclusive="58229" elapsedInclusivePercent="4.0" id="1150647" name="System.StrLen(const char*)"/>
  <function count="1" elapsedExclusive="12477" elapsedExclusivePercent="5.1" elapsedInclusive="12477" elapsedInclusivePercent="0.8" id="1150136" name="System.endl()"/>
  <function count="1" elapsedExclusive="0" elapsedExclusivePercent="0" elapsedInclusive="3604" elapsedInclusivePercent="0.2" id="1178992" name="System.operator+(const String&lt;char>&amp;, const String&lt;char>&amp;)"/>
  <function count="2" elapsedExclusive="0" elapsedExclusivePercent="0" elapsedInclusive="4990" elapsedInclusivePercent="0.3" id="1178991" name="System.operator+(const String&lt;char>&amp;, const char*)"/>
  <function count="1" elapsedExclusive="277" elapsedExclusivePercent="0.1" elapsedInclusive="14141" elapsedInclusivePercent="0.9" id="1178990" name="System.operator+(const char*, const String&lt;char>&amp;)"/>
  <function count="1" elapsedExclusive="0" elapsedExclusivePercent="0" elapsedInclusive="277" elapsedInclusivePercent="0.0" id="1308658" name="System.operator==(const RandomAccessIter&lt;String&lt;char>, String&lt;char>&amp;, String&lt;char>*>&amp;, const RandomAccessIter&lt;String&lt;char>, String&lt;char>&amp;, String&lt;char>*>&amp;)"/>
  <function count="66" elapsedExclusive="277" elapsedExclusivePercent="0.1" elapsedInclusive="30218" elapsedInclusivePercent="2.1" id="1158868" name="System.operator==(const RandomAccessIter&lt;char, const char&amp;, const char*>&amp;, const RandomAccessIter&lt;char, const char&amp;, const char*>&amp;)"/>
  <function count="18" elapsedExclusive="0" elapsedExclusivePercent="0" elapsedInclusive="8596" elapsedInclusivePercent="0.6" id="1158938" name="System.operator==(const String&lt;char>&amp;, const String&lt;char>&amp;)"/>
  <function count="1" elapsedExclusive="0" elapsedExclusivePercent="0" elapsedInclusive="0" elapsedInclusivePercent="0" id="1150676" name="UniquePtr&lt;System.Ascii.CharClassTable>.@constructor(UniquePtr&lt;System.Ascii.CharClassTable>, CharClassTable*)"/>
  <function count="1" elapsedExclusive="555" elapsedExclusivePercent="0.2" elapsedInclusive="555" elapsedInclusivePercent="0.0" id="1150682" name="UniquePtr&lt;System.Ascii.CharClassTable>.@destructor(UniquePtr&lt;System.Ascii.CharClassTable>)"/>
  <function count="1" elapsedExclusive="277" elapsedExclusivePercent="0.1" elapsedInclusive="277" elapsedInclusivePercent="0.0" id="1150691" name="UniquePtr&lt;System.Ascii.CharClassTable>.operator*(UniquePtr&lt;System.Ascii.CharClassTable>)"/>
  <function count="1" elapsedExclusive="0" elapsedExclusivePercent="0" elapsedInclusive="0" elapsedInclusivePercent="0" id="1299659" name="UniquePtr&lt;System.Exception>.@constructor(UniquePtr&lt;System.Exception>, Exception*)"/>
  <function count="1" elapsedExclusive="278" elapsedExclusivePercent="0.1" elapsedInclusive="1941" elapsedInclusivePercent="0.1" id="1299665" name="UniquePtr&lt;System.Exception>.@destructor(UniquePtr&lt;System.Exception>)"/>
  <function count="1" elapsedExclusive="0" elapsedExclusivePercent="0" elapsedInclusive="0" elapsedInclusivePercent="0" id="1299674" name="UniquePtr&lt;System.Exception>.operator*(UniquePtr&lt;System.Exception>)"/>
  <function count="1" elapsedExclusive="0" elapsedExclusivePercent="0" elapsedInclusive="1329253" elapsedInclusivePercent="93.0" id="1291743" name="main(int, const char**)"/>
</profile>
