{
    "dependsOnProjects" : 
    [
    ]
    , 
    "error" : "", 
    "fileInfos" : 
    [
        {
            "content" : "", 
            "fileHash" : "212C7AA8D5E584079D51CF3B648AEACE0B4254C8", 
            "fileId" : "main_8CCB072BA5F37BE2E8876B53C0B33DFEF56E4860", 
            "filePath" : "C:\/work\/cmajorm\/cmajor\/projects\/examples\/HexDump\/main.cm", 
            "info" : ""
        }
    ]
    , 
    "info" : "", 
    "projectFilePath" : "C:\/work\/cmajorm\/cmajor\/projects\/examples\/HexDump\/hexdump.cmp", 
    "projectHash" : "183737EA8FA8D26B5885AE15657DF6804425335D", 
    "projectId" : "project_HexDump_F95269FF6D2A6335320CA4F56E17E54133DF9334", 
    "projectName" : "HexDump", 
    "target" : "program"
}
