{
    "dependsOnProjects" : 
    [
    ]
    , 
    "error" : "", 
    "fileInfos" : 
    [
        {
            "content" : "", 
            "fileHash" : "81064E5E8793BFB750F6CA3B19E6D599991B7D6B", 
            "fileId" : "FiberTest_CD92682744E56E620D44C2821AFB1E3417C0BECC", 
            "filePath" : "D:\/work\/cmajorm\/cmajor\/doc\/code\/fiber\/FiberTest.cm", 
            "info" : ""
        }
    ]
    , 
    "info" : "", 
    "projectFilePath" : "D:\/work\/cmajorm\/cmajor\/doc\/code\/fiber\/FiberTest.cmp", 
    "projectHash" : "ED46B0E178F4C25A816CB445A251C2D0C398F491", 
    "projectId" : "project_FiberTest_1AACBE88E997C1E728F2F00A738CA8C1008D2629", 
    "projectName" : "FiberTest", 
    "target" : "program"
}
