{
    "dependsOnProjects" : 
    [
    ]
    , 
    "error" : "", 
    "fileInfos" : 
    [
        {
            "content" : "", 
            "fileHash" : "221CBA56122E53D5B6961161A8D6BFFE4705C568", 
            "fileId" : "Main_3BEAB0BB73594ACA5038218B63CB06D86BFEE8D3", 
            "filePath" : "D:\/work\/cmajorm\/cmajor\/projects\/examples\/sted\/Main.cm", 
            "info" : ""
        }
    ]
    , 
    "info" : "", 
    "projectFilePath" : "D:\/work\/cmajorm\/cmajor\/projects\/examples\/sted\/sted.cmp", 
    "projectHash" : "05D385AE0A743927B859ED068F68AF4F297BF8A7", 
    "projectId" : "project_sted_7D79119C63A19310C6A6B919E005B069BC8447DF", 
    "projectName" : "sted", 
    "target" : "program"
}
